quart_sqlalchemy-3.0.3.dist-info/METADATA
quart_sqlalchemy-3.0.3.dist-info/WHEEL
quart_sqlalchemy-3.0.3.dist-info/licenses/LICENSE.rst
quart_sqlalchemy/__init__.py
quart_sqlalchemy/bind.py
quart_sqlalchemy/config.py
quart_sqlalchemy/framework/__init__.py
quart_sqlalchemy/framework/cli.py
quart_sqlalchemy/framework/extension.py
quart_sqlalchemy/model/.mypy_cache/.gitignore
quart_sqlalchemy/model/.mypy_cache/3.7/@plugins_snapshot.json
quart_sqlalchemy/model/.mypy_cache/3.7/__future__.data.json
quart_sqlalchemy/model/.mypy_cache/3.7/__future__.meta.json
quart_sqlalchemy/model/.mypy_cache/3.7/_ast.data.json
quart_sqlalchemy/model/.mypy_cache/3.7/_ast.meta.json
quart_sqlalchemy/model/.mypy_cache/3.7/_codecs.data.json
quart_sqlalchemy/model/.mypy_cache/3.7/_codecs.meta.json
quart_sqlalchemy/model/.mypy_cache/3.7/_collections_abc.data.json
quart_sqlalchemy/model/.mypy_cache/3.7/_collections_abc.meta.json
quart_sqlalchemy/model/.mypy_cache/3.7/_csv.data.json
quart_sqlalchemy/model/.mypy_cache/3.7/_csv.meta.json
quart_sqlalchemy/model/.mypy_cache/3.7/_decimal.data.json
quart_sqlalchemy/model/.mypy_cache/3.7/_decimal.meta.json
quart_sqlalchemy/model/.mypy_cache/3.7/_heapq.data.json
quart_sqlalchemy/model/.mypy_cache/3.7/_heapq.meta.json
quart_sqlalchemy/model/.mypy_cache/3.7/_operator.data.json
quart_sqlalchemy/model/.mypy_cache/3.7/_operator.meta.json
quart_sqlalchemy/model/.mypy_cache/3.7/_random.data.json
quart_sqlalchemy/model/.mypy_cache/3.7/_random.meta.json
quart_sqlalchemy/model/.mypy_cache/3.7/_socket.data.json
quart_sqlalchemy/model/.mypy_cache/3.7/_socket.meta.json
quart_sqlalchemy/model/.mypy_cache/3.7/_stat.data.json
quart_sqlalchemy/model/.mypy_cache/3.7/_stat.meta.json
quart_sqlalchemy/model/.mypy_cache/3.7/_typeshed/__init__.data.json
quart_sqlalchemy/model/.mypy_cache/3.7/_typeshed/__init__.meta.json
quart_sqlalchemy/model/.mypy_cache/3.7/_typeshed/wsgi.data.json
quart_sqlalchemy/model/.mypy_cache/3.7/_typeshed/wsgi.meta.json
quart_sqlalchemy/model/.mypy_cache/3.7/_warnings.data.json
quart_sqlalchemy/model/.mypy_cache/3.7/_warnings.meta.json
quart_sqlalchemy-3.0.3.dist-info/RECORD
