Metadata-Version: 2.1
Name: quart-sqlalchemy
Version: 3.0.3
Summary: SQLAlchemy for humans, with framework adapter for Quart.
Author-Email: Joe Black <me@joeblack.nyc>
License: MIT
Project-URL: Homepage, https://github.com/joeblackwaslike/quart-sqlalchemy
Project-URL: Bug tracker, https://github.com/joeblackwaslike/quart-sqlalchemy/issues
Requires-Python: >=3.8
Requires-Dist: quart<0.20.0,>=0.18.3
Requires-Dist: werkzeug<3.1.0,>=2.2.0
Requires-Dist: blinker<1.7,>=1.5
Requires-Dist: SQLAlchemy[asyncio]<2.1.0,>=2.0.0
Requires-Dist: SQLAlchemy-Utils
Requires-Dist: anyio~=3.3.4
Requires-Dist: pydantic~=1.10.13
Requires-Dist: tenacity~=8.0.1
Requires-Dist: sqlapagination
Requires-Dist: exceptiongroup
